<?xml version = '1.0' encoding = 'UTF-8'?>
<Table class="oracle.dbtools.crest.model.design.relational.Table" id="C3FDF692-1B02-4D01-0926-AE5B6EDDAAEA" directorySegmentName="seg_0" name="INPUT_FORECAST_INTERVAL">
<createdBy>clay.rowland</createdBy>
<createdTime>2013-06-19 21:11:54 UTC</createdTime>
<comment>This &quot;temporary table&quot; represents the format of the forecast flat file.</comment>
<ownerDesignName>Project Contact Center Production Planning</ownerDesignName>
<shouldEngineer>false</shouldEngineer>
<typeID>5</typeID>
<fonts>
<FontObject class="oracle.dbtools.crest.model.design.FontObjectWr">
<foType>Title</foType>
<fontStyle>1</fontStyle>
<colorRGB>-16776961</colorRGB>
</FontObject>
<FontObject class="oracle.dbtools.crest.model.design.FontObjectWr">
<foType>Column</foType>
<colorRGB>-16777216</colorRGB>
</FontObject>
<FontObject class="oracle.dbtools.crest.model.design.FontObjectWr">
<foType>Datatype</foType>
<colorRGB>-16744448</colorRGB>
</FontObject>
<FontObject class="oracle.dbtools.crest.model.design.FontObjectWr">
<foType>PK Element</foType>
<colorRGB>-16776961</colorRGB>
</FontObject>
<FontObject class="oracle.dbtools.crest.model.design.FontObjectWr">
<foType>FK Element</foType>
<colorRGB>-16777216</colorRGB>
</FontObject>
<FontObject class="oracle.dbtools.crest.model.design.FontObjectWr">
<foType>UK Element</foType>
<colorRGB>-16776961</colorRGB>
</FontObject>
<FontObject class="oracle.dbtools.crest.model.design.FontObjectWr">
<foType>Not Null</foType>
<colorRGB>-65536</colorRGB>
</FontObject>
<FontObject class="oracle.dbtools.crest.model.design.FontObjectWr">
<foType>Key</foType>
<colorRGB>-16777216</colorRGB>
</FontObject>
</fonts>
<columns>
<Column class="oracle.dbtools.crest.model.design.relational.Column" name="PRODUCTION_PLAN_NAME" id="0B74D692-1C12-41FE-F94A-EC41EE3617A8">
<createdBy>clay.rowland</createdBy>
<createdTime>2013-06-19 21:11:54 UTC</createdTime>
<ownerDesignName>Project Contact Center Production Planning</ownerDesignName>
<nullsAllowed>true</nullsAllowed>
<useDomainConstraints>false</useDomainConstraints>
<use>1</use>
<logicalDatatype>LOGDT024</logicalDatatype>
<autoIncrementCycle>false</autoIncrementCycle>
</Column>
<Column class="oracle.dbtools.crest.model.design.relational.Column" name="HORIZON_START_DATE" id="68A03C8F-233A-B349-5EE9-85CA1FDD89B7">
<createdBy>clay.rowland</createdBy>
<createdTime>2013-06-19 21:11:54 UTC</createdTime>
<ownerDesignName>Project Contact Center Production Planning</ownerDesignName>
<nullsAllowed>true</nullsAllowed>
<useDomainConstraints>false</useDomainConstraints>
<use>1</use>
<logicalDatatype>LOGDT007</logicalDatatype>
<autoIncrementCycle>false</autoIncrementCycle>
</Column>
<Column class="oracle.dbtools.crest.model.design.relational.Column" name="HORIZON_END_DATE" id="17697CDC-D347-C9E0-1C97-8A09E1433378">
<createdBy>clay.rowland</createdBy>
<createdTime>2013-06-19 21:11:54 UTC</createdTime>
<ownerDesignName>Project Contact Center Production Planning</ownerDesignName>
<nullsAllowed>true</nullsAllowed>
<useDomainConstraints>false</useDomainConstraints>
<use>1</use>
<logicalDatatype>LOGDT007</logicalDatatype>
<autoIncrementCycle>false</autoIncrementCycle>
</Column>
<Column class="oracle.dbtools.crest.model.design.relational.Column" name="INTERVAL_DATE" id="354465CE-896A-08A7-FD03-49B413E87087">
<createdBy>clay.rowland</createdBy>
<createdTime>2013-06-19 21:11:54 UTC</createdTime>
<ownerDesignName>Project Contact Center Production Planning</ownerDesignName>
<nullsAllowed>true</nullsAllowed>
<useDomainConstraints>false</useDomainConstraints>
<use>1</use>
<logicalDatatype>LOGDT007</logicalDatatype>
<autoIncrementCycle>false</autoIncrementCycle>
</Column>
<Column class="oracle.dbtools.crest.model.design.relational.Column" name="INTERVAL_START" id="26A4B23F-9CE0-FC68-F76A-EB6A0C8DD33C">
<createdBy>clay.rowland</createdBy>
<createdTime>2013-06-19 21:11:54 UTC</createdTime>
<ownerDesignName>Project Contact Center Production Planning</ownerDesignName>
<nullsAllowed>true</nullsAllowed>
<useDomainConstraints>false</useDomainConstraints>
<use>1</use>
<logicalDatatype>LOGDT024</logicalDatatype>
<autoIncrementCycle>false</autoIncrementCycle>
</Column>
<Column class="oracle.dbtools.crest.model.design.relational.Column" name="INTERVAL_END" id="43417AA3-BA8E-0899-2B85-ECB50FE75498">
<createdBy>clay.rowland</createdBy>
<createdTime>2013-06-19 21:11:54 UTC</createdTime>
<ownerDesignName>Project Contact Center Production Planning</ownerDesignName>
<nullsAllowed>true</nullsAllowed>
<useDomainConstraints>false</useDomainConstraints>
<use>1</use>
<logicalDatatype>LOGDT024</logicalDatatype>
<autoIncrementCycle>false</autoIncrementCycle>
</Column>
<Column class="oracle.dbtools.crest.model.design.relational.Column" name="UNIT_OF_WORK_NAME" id="BD3B599D-C629-3482-F11E-C627B9A268D6">
<createdBy>clay.rowland</createdBy>
<createdTime>2013-06-19 21:11:54 UTC</createdTime>
<ownerDesignName>Project Contact Center Production Planning</ownerDesignName>
<nullsAllowed>true</nullsAllowed>
<useDomainConstraints>false</useDomainConstraints>
<use>1</use>
<logicalDatatype>LOGDT024</logicalDatatype>
<autoIncrementCycle>false</autoIncrementCycle>
</Column>
<Column class="oracle.dbtools.crest.model.design.relational.Column" name="CONTACTS_CREATED" id="9AE199B4-1E24-C5A2-A05A-B9A39FE6603A">
<createdBy>clay.rowland</createdBy>
<createdTime>2013-06-19 21:11:54 UTC</createdTime>
<ownerDesignName>Project Contact Center Production Planning</ownerDesignName>
<nullsAllowed>true</nullsAllowed>
<useDomainConstraints>false</useDomainConstraints>
<use>1</use>
<logicalDatatype>LOGDT019</logicalDatatype>
<autoIncrementCycle>false</autoIncrementCycle>
</Column>
</columns>
</Table>