<?xml version = '1.0' encoding = 'UTF-8'?>
<TableProxyOraclev11g class="oracle.dbtools.crest.model.design.storage.oracle.v11g.TableProxyOraclev11g" name="PP_D_SEGMENT" id="B2433D44-C7C9-10A6-214C-24885D512187" directorySegmentName="seg_0">
<createdBy>34601</createdBy>
<createdTime>2013-06-10 15:54:25 UTC</createdTime>
<ownerDesignName>Production Planning Data Model</ownerDesignName>
<logging>YES</logging>
<columnProxies>
<ColumnProxy class="oracle.dbtools.crest.model.design.storage.oracle.v11g.ColumnProxyOraclev11g" name="SEGMENT_ID" id="02F4382B-BDF1-0344-0F52-B733FADE6A39">
<createdBy>34601</createdBy>
<createdTime>2013-06-10 15:54:25 UTC</createdTime>
<ownerDesignName>Production Planning Data Model</ownerDesignName>
</ColumnProxy>
<ColumnProxy class="oracle.dbtools.crest.model.design.storage.oracle.v11g.ColumnProxyOraclev11g" name="SEGMENT_NAME" id="6B1F9354-EFA6-CB66-0B16-984D8FEF17F2">
<createdBy>34601</createdBy>
<createdTime>2013-06-10 15:54:25 UTC</createdTime>
<ownerDesignName>Production Planning Data Model</ownerDesignName>
</ColumnProxy>
</columnProxies>
<primaryKeys>
<PrimaryKey class="oracle.dbtools.crest.model.design.storage.oracle.v10g.PKProxyOraclev10g" name="PK_D_SEGMENT_LKUP" id="52D4A586-7977-AEBB-B2D3-C55DD7C18AE9">
<createdBy>34601</createdBy>
<createdTime>2013-06-10 15:54:25 UTC</createdTime>
<ownerDesignName>Production Planning Data Model</ownerDesignName>
<sortedRows>SORTED</sortedRows>
<indexSort>SORTED</indexSort>
</PrimaryKey>
</primaryKeys>
<uniqueKeys>
<UniqueKey class="oracle.dbtools.crest.model.design.storage.oracle.v10g.UniqueOraclev10g" name="D_SEGMENT_UNK" id="185E2569-027D-F80C-4FE8-60353F42FC5E">
<createdBy>34601</createdBy>
<createdTime>2013-06-10 15:54:25 UTC</createdTime>
<ownerDesignName>Production Planning Data Model</ownerDesignName>
<sortedRows>SORTED</sortedRows>
<indexSort>SORTED</indexSort>
</UniqueKey>
</uniqueKeys>
</TableProxyOraclev11g>