<?xml version = '1.0' encoding = 'UTF-8'?>
<Table class="oracle.dbtools.crest.model.design.relational.Table" id="ED687BC2-840A-5EE8-E0AC-5D67E9C316BB" directorySegmentName="seg_0" name="PP_F_ACTUALS">
<createdBy>34601</createdBy>
<createdTime>2013-06-26 17:49:54 UTC</createdTime>
<ownerDesignName>Production Planning Data Model</ownerDesignName>
<pkName>FPP_PK</pkName>
<fonts>
<FontObject class="oracle.dbtools.crest.model.design.FontObjectWr">
<foType>Title</foType>
<fontStyle>1</fontStyle>
<colorRGB>-16776961</colorRGB>
</FontObject>
<FontObject class="oracle.dbtools.crest.model.design.FontObjectWr">
<foType>Column</foType>
<colorRGB>-16777216</colorRGB>
</FontObject>
<FontObject class="oracle.dbtools.crest.model.design.FontObjectWr">
<foType>Datatype</foType>
<colorRGB>-16744448</colorRGB>
</FontObject>
<FontObject class="oracle.dbtools.crest.model.design.FontObjectWr">
<foType>PK Element</foType>
<colorRGB>-16776961</colorRGB>
</FontObject>
<FontObject class="oracle.dbtools.crest.model.design.FontObjectWr">
<foType>FK Element</foType>
<colorRGB>-16777216</colorRGB>
</FontObject>
<FontObject class="oracle.dbtools.crest.model.design.FontObjectWr">
<foType>UK Element</foType>
<colorRGB>-16776961</colorRGB>
</FontObject>
<FontObject class="oracle.dbtools.crest.model.design.FontObjectWr">
<foType>Not Null</foType>
<colorRGB>-65536</colorRGB>
</FontObject>
<FontObject class="oracle.dbtools.crest.model.design.FontObjectWr">
<foType>Key</foType>
<colorRGB>-16777216</colorRGB>
</FontObject>
</fonts>
<columns>
<Column class="oracle.dbtools.crest.model.design.relational.Column" name="ACTUALS_ID" id="5EB03632-D432-3B5C-237E-29CF216DC28F">
<createdBy>34601</createdBy>
<createdTime>2013-06-26 17:49:54 UTC</createdTime>
<ownerDesignName>Production Planning Data Model</ownerDesignName>
<use>0</use>
<logicalDatatype>LOGDT019</logicalDatatype>
<domain>71174A0E-2F82-6F26-2DD5-9657FF4121C1</domain>
<autoIncrementCycle>false</autoIncrementCycle>
</Column>
<Column class="oracle.dbtools.crest.model.design.relational.Column" name="D_DATE" id="52E758E8-7808-D7EA-53F5-136A903C90A7">
<createdBy>34601</createdBy>
<createdTime>2013-06-26 17:49:54 UTC</createdTime>
<ownerDesignName>Production Planning Data Model</ownerDesignName>
<use>0</use>
<logicalDatatype>LOGDT007</logicalDatatype>
<domain>8E1B7CAF-2424-3F25-79BC-7C1B3F75651C</domain>
<delegate>81440A63-01DE-1F48-9042-8B4F607548A8</delegate>
<autoIncrementCycle>false</autoIncrementCycle>
<associations>
<colAssociation fkAssociation="2D84B12C-B11D-0C43-AFB2-05A5D22C61D4" referredColumn="81440A63-01DE-1F48-9042-8B4F607548A8"/>
</associations>
</Column>
<Column class="oracle.dbtools.crest.model.design.relational.Column" name="D_HOUR" id="CD7DDE3D-68EF-6DE9-EE92-B32A719122E8">
<createdBy>34601</createdBy>
<createdTime>2013-06-26 17:49:54 UTC</createdTime>
<ownerDesignName>Production Planning Data Model</ownerDesignName>
<use>0</use>
<logicalDatatype>LOGDT019</logicalDatatype>
<domain>71174A0E-2F82-6F26-2DD5-9657FF4121C1</domain>
<delegate>A4251FFB-D639-C7AC-CF40-510C577FDBAF</delegate>
<autoIncrementCycle>false</autoIncrementCycle>
<associations>
<colAssociation fkAssociation="0DA1CE65-B481-CEA2-2BE1-A947B4C2C9A0" referredColumn="A4251FFB-D639-C7AC-CF40-510C577FDBAF"/>
</associations>
</Column>
<Column class="oracle.dbtools.crest.model.design.relational.Column" name="UOW_ID" id="BB3C52DF-89E3-23EC-1E65-57F5A8E0CC87">
<createdBy>34601</createdBy>
<createdTime>2013-06-26 17:49:54 UTC</createdTime>
<ownerDesignName>Production Planning Data Model</ownerDesignName>
<use>0</use>
<logicalDatatype>LOGDT019</logicalDatatype>
<domain>71174A0E-2F82-6F26-2DD5-9657FF4121C1</domain>
<delegate>E1E86E77-930C-07AE-ABCD-1DFA87E9D864</delegate>
<autoIncrementCycle>false</autoIncrementCycle>
<associations>
<colAssociation fkAssociation="60CBFD90-A08C-25AE-EE5B-2FE9991C9D77" referredColumn="E1E86E77-930C-07AE-ABCD-1DFA87E9D864"/>
</associations>
</Column>
<Column class="oracle.dbtools.crest.model.design.relational.Column" name="PROJECT_ID" id="6597025F-9706-3566-51B2-5726189979FA">
<createdBy>34601</createdBy>
<createdTime>2013-06-28 17:08:38 UTC</createdTime>
<ownerDesignName>Production Planning Data Model</ownerDesignName>
<use>0</use>
<logicalDatatype>LOGDT019</logicalDatatype>
<domain>71174A0E-2F82-6F26-2DD5-9657FF4121C1</domain>
<delegate>D125469C-655C-0564-06C6-5F6F0C2AFDF8</delegate>
<autoIncrementCycle>false</autoIncrementCycle>
<associations>
<colAssociation fkAssociation="EAF171DE-41EE-443D-B04C-C931ED1DCA8D" referredColumn="D125469C-655C-0564-06C6-5F6F0C2AFDF8"/>
</associations>
</Column>
<Column class="oracle.dbtools.crest.model.design.relational.Column" name="PROGRAM_ID" id="1DB10DB5-7EA0-EE78-4FF8-D4719A2B2BA5">
<createdBy>34601</createdBy>
<createdTime>2013-06-28 17:08:38 UTC</createdTime>
<ownerDesignName>Production Planning Data Model</ownerDesignName>
<use>0</use>
<logicalDatatype>LOGDT019</logicalDatatype>
<domain>71174A0E-2F82-6F26-2DD5-9657FF4121C1</domain>
<delegate>E9CD6F2D-5266-E8B7-A951-F5722F954AB6</delegate>
<autoIncrementCycle>false</autoIncrementCycle>
<associations>
<colAssociation fkAssociation="9471E788-F3C5-FC6A-A791-51795DCD560A" referredColumn="E9CD6F2D-5266-E8B7-A951-F5722F954AB6"/>
</associations>
</Column>
<Column class="oracle.dbtools.crest.model.design.relational.Column" name="GEOGRAPHY_MASTER_ID" id="1E2D38C0-B066-E120-6DBF-3697FD496337">
<createdBy>34601</createdBy>
<createdTime>2013-06-28 17:08:53 UTC</createdTime>
<ownerDesignName>Production Planning Data Model</ownerDesignName>
<use>0</use>
<logicalDatatype>LOGDT019</logicalDatatype>
<domain>71174A0E-2F82-6F26-2DD5-9657FF4121C1</domain>
<delegate>9A8E164D-4373-E718-4426-C95139355019</delegate>
<autoIncrementCycle>false</autoIncrementCycle>
<associations>
<colAssociation fkAssociation="8CDB645D-68B8-D8F0-276B-A6B85DE087DD" referredColumn="9A8E164D-4373-E718-4426-C95139355019"/>
</associations>
</Column>
<Column class="oracle.dbtools.crest.model.design.relational.Column" name="ACTL_ARRIVAL" id="A0D351F0-032C-420A-3F13-02611967BA2D">
<createdBy>34601</createdBy>
<createdTime>2013-06-26 17:49:54 UTC</createdTime>
<ownerDesignName>Production Planning Data Model</ownerDesignName>
<nullsAllowed>true</nullsAllowed>
<use>0</use>
<logicalDatatype>LOGDT019</logicalDatatype>
<domain>71174A0E-2F82-6F26-2DD5-9657FF4121C1</domain>
<autoIncrementCycle>false</autoIncrementCycle>
</Column>
<Column class="oracle.dbtools.crest.model.design.relational.Column" name="ACTL_COMPLETION" id="0D14F723-535C-B68B-9AA0-AF5C91238DF8">
<createdBy>34601</createdBy>
<createdTime>2013-06-26 17:49:54 UTC</createdTime>
<ownerDesignName>Production Planning Data Model</ownerDesignName>
<nullsAllowed>true</nullsAllowed>
<use>0</use>
<logicalDatatype>LOGDT019</logicalDatatype>
<domain>71174A0E-2F82-6F26-2DD5-9657FF4121C1</domain>
<autoIncrementCycle>false</autoIncrementCycle>
</Column>
<Column class="oracle.dbtools.crest.model.design.relational.Column" name="ACTL_INVENTORY" id="746A8E1D-B0B0-13A7-EC25-F31CB06E507D">
<createdBy>34601</createdBy>
<createdTime>2013-06-26 17:49:54 UTC</createdTime>
<ownerDesignName>Production Planning Data Model</ownerDesignName>
<nullsAllowed>true</nullsAllowed>
<use>0</use>
<logicalDatatype>LOGDT019</logicalDatatype>
<domain>71174A0E-2F82-6F26-2DD5-9657FF4121C1</domain>
<autoIncrementCycle>false</autoIncrementCycle>
</Column>
<Column class="oracle.dbtools.crest.model.design.relational.Column" name="ACTL_INVENTORY_AGE_AVG" id="EEE0FFD2-7972-CDD3-0AC2-70AE49F8D9E8">
<createdBy>34601</createdBy>
<createdTime>2013-06-26 17:49:54 UTC</createdTime>
<ownerDesignName>Production Planning Data Model</ownerDesignName>
<nullsAllowed>true</nullsAllowed>
<use>0</use>
<logicalDatatype>LOGDT019</logicalDatatype>
<domain>4033C4AA-C617-34F3-172E-603E37AEC046</domain>
<autoIncrementCycle>false</autoIncrementCycle>
</Column>
<Column class="oracle.dbtools.crest.model.design.relational.Column" name="ACTL_INVENTORY_AGE_MIN" id="36108559-6EBA-CDF3-F84B-ADC7A6FC8AFC">
<createdBy>34601</createdBy>
<createdTime>2013-06-26 17:49:54 UTC</createdTime>
<ownerDesignName>Production Planning Data Model</ownerDesignName>
<nullsAllowed>true</nullsAllowed>
<use>0</use>
<logicalDatatype>LOGDT019</logicalDatatype>
<domain>4033C4AA-C617-34F3-172E-603E37AEC046</domain>
<autoIncrementCycle>false</autoIncrementCycle>
</Column>
<Column class="oracle.dbtools.crest.model.design.relational.Column" name="ACTL_INVENTORY_AGE_MAX" id="0FF6D2F1-5283-AF8D-0BCB-79F6AB0D3CA4">
<createdBy>34601</createdBy>
<createdTime>2013-06-26 17:49:54 UTC</createdTime>
<ownerDesignName>Production Planning Data Model</ownerDesignName>
<nullsAllowed>true</nullsAllowed>
<use>0</use>
<logicalDatatype>LOGDT019</logicalDatatype>
<domain>4033C4AA-C617-34F3-172E-603E37AEC046</domain>
<autoIncrementCycle>false</autoIncrementCycle>
</Column>
<Column class="oracle.dbtools.crest.model.design.relational.Column" name="ACTL_INVENTORY_AGE_MEAN" id="0D040E7E-EE17-3374-AD9B-FC81551290AA">
<createdBy>34601</createdBy>
<createdTime>2013-06-26 17:49:54 UTC</createdTime>
<ownerDesignName>Production Planning Data Model</ownerDesignName>
<nullsAllowed>true</nullsAllowed>
<use>0</use>
<logicalDatatype>LOGDT019</logicalDatatype>
<domain>4033C4AA-C617-34F3-172E-603E37AEC046</domain>
<autoIncrementCycle>false</autoIncrementCycle>
</Column>
<Column class="oracle.dbtools.crest.model.design.relational.Column" name="ACTL_INVENTORY_AGE_MEDIAN" id="FF6AD7B2-5094-137C-0DB9-545FBE4ED3D2">
<createdBy>34601</createdBy>
<createdTime>2013-06-26 17:49:54 UTC</createdTime>
<ownerDesignName>Production Planning Data Model</ownerDesignName>
<nullsAllowed>true</nullsAllowed>
<use>0</use>
<logicalDatatype>LOGDT019</logicalDatatype>
<domain>4033C4AA-C617-34F3-172E-603E37AEC046</domain>
<autoIncrementCycle>false</autoIncrementCycle>
</Column>
<Column class="oracle.dbtools.crest.model.design.relational.Column" name="ACTL_INVENTORY_AGE_SD" id="56B3EAEB-6B6E-2930-889D-A87C0000DDC8">
<createdBy>34601</createdBy>
<createdTime>2013-06-26 17:49:54 UTC</createdTime>
<ownerDesignName>Production Planning Data Model</ownerDesignName>
<nullsAllowed>true</nullsAllowed>
<use>0</use>
<logicalDatatype>LOGDT019</logicalDatatype>
<domain>4033C4AA-C617-34F3-172E-603E37AEC046</domain>
<autoIncrementCycle>false</autoIncrementCycle>
</Column>
<Column class="oracle.dbtools.crest.model.design.relational.Column" name="ACTL_INVENTORY_JEOPARDY" id="81A53DA2-409B-24BC-1B8A-E563AB57E434">
<createdBy>34601</createdBy>
<createdTime>2013-06-26 17:49:54 UTC</createdTime>
<ownerDesignName>Production Planning Data Model</ownerDesignName>
<nullsAllowed>true</nullsAllowed>
<use>0</use>
<logicalDatatype>LOGDT019</logicalDatatype>
<domain>71174A0E-2F82-6F26-2DD5-9657FF4121C1</domain>
<autoIncrementCycle>false</autoIncrementCycle>
</Column>
<Column class="oracle.dbtools.crest.model.design.relational.Column" name="ACTL_HANDLE_TIME_AVG" id="664CCE98-75F9-5D11-A4DA-F77D292BA0C9">
<createdBy>34601</createdBy>
<createdTime>2013-06-26 17:49:54 UTC</createdTime>
<ownerDesignName>Production Planning Data Model</ownerDesignName>
<nullsAllowed>true</nullsAllowed>
<use>0</use>
<logicalDatatype>LOGDT019</logicalDatatype>
<domain>ABF6B50B-A8C2-FAED-8F01-DEBA05EDCE34</domain>
<autoIncrementCycle>false</autoIncrementCycle>
</Column>
<Column class="oracle.dbtools.crest.model.design.relational.Column" name="ACTL_HANDLE_TIME_MIN" id="4A365F8E-3888-8024-1508-51F60C7D79AD">
<createdBy>34601</createdBy>
<createdTime>2013-06-26 17:49:54 UTC</createdTime>
<ownerDesignName>Production Planning Data Model</ownerDesignName>
<nullsAllowed>true</nullsAllowed>
<use>0</use>
<logicalDatatype>LOGDT019</logicalDatatype>
<domain>ABF6B50B-A8C2-FAED-8F01-DEBA05EDCE34</domain>
<autoIncrementCycle>false</autoIncrementCycle>
</Column>
<Column class="oracle.dbtools.crest.model.design.relational.Column" name="ACTL_HANDLE_TIME_MAX" id="67500CFC-D62D-7A33-2095-46ED7A43D6E2">
<createdBy>34601</createdBy>
<createdTime>2013-06-26 17:49:54 UTC</createdTime>
<ownerDesignName>Production Planning Data Model</ownerDesignName>
<nullsAllowed>true</nullsAllowed>
<use>0</use>
<logicalDatatype>LOGDT019</logicalDatatype>
<domain>ABF6B50B-A8C2-FAED-8F01-DEBA05EDCE34</domain>
<autoIncrementCycle>false</autoIncrementCycle>
</Column>
<Column class="oracle.dbtools.crest.model.design.relational.Column" name="ACTL_HANDLE_TIME_MEAN" id="6762262F-D2EB-5459-D730-10A530653E75">
<createdBy>34601</createdBy>
<createdTime>2013-06-26 17:49:54 UTC</createdTime>
<ownerDesignName>Production Planning Data Model</ownerDesignName>
<nullsAllowed>true</nullsAllowed>
<use>0</use>
<logicalDatatype>LOGDT019</logicalDatatype>
<domain>ABF6B50B-A8C2-FAED-8F01-DEBA05EDCE34</domain>
<autoIncrementCycle>false</autoIncrementCycle>
</Column>
<Column class="oracle.dbtools.crest.model.design.relational.Column" name="ACTL_HANDLE_TIME_MEDIAN" id="5856B78C-2860-EECC-2148-C691ECF6D010">
<createdBy>34601</createdBy>
<createdTime>2013-06-26 17:49:54 UTC</createdTime>
<ownerDesignName>Production Planning Data Model</ownerDesignName>
<nullsAllowed>true</nullsAllowed>
<use>0</use>
<logicalDatatype>LOGDT019</logicalDatatype>
<domain>ABF6B50B-A8C2-FAED-8F01-DEBA05EDCE34</domain>
<autoIncrementCycle>false</autoIncrementCycle>
</Column>
<Column class="oracle.dbtools.crest.model.design.relational.Column" name="ACTL_HANDLE_TIME_SD" id="26AABE8F-7CE3-A087-D301-F9D537C10B8D">
<createdBy>34601</createdBy>
<createdTime>2013-06-26 17:49:54 UTC</createdTime>
<ownerDesignName>Production Planning Data Model</ownerDesignName>
<nullsAllowed>true</nullsAllowed>
<use>0</use>
<logicalDatatype>LOGDT019</logicalDatatype>
<domain>ABF6B50B-A8C2-FAED-8F01-DEBA05EDCE34</domain>
<autoIncrementCycle>false</autoIncrementCycle>
</Column>
<Column class="oracle.dbtools.crest.model.design.relational.Column" name="ACTL_STAFF_HOURS" id="68F56936-CE1A-FC7D-2F1F-C18841006EEE">
<createdBy>34601</createdBy>
<createdTime>2013-06-26 17:49:54 UTC</createdTime>
<ownerDesignName>Production Planning Data Model</ownerDesignName>
<nullsAllowed>true</nullsAllowed>
<use>0</use>
<logicalDatatype>LOGDT019</logicalDatatype>
<domain>ABF6B50B-A8C2-FAED-8F01-DEBA05EDCE34</domain>
<autoIncrementCycle>false</autoIncrementCycle>
</Column>
</columns>
<indexes>
<ind_PK_UK class="oracle.dbtools.crest.model.design.relational.Index" id="E1BD890E-5F8A-A154-6274-C979BE2FC1F8" name="PP_F_ACTUALS_PK">
<createdBy>34601</createdBy>
<createdTime>2013-06-26 17:49:54 UTC</createdTime>
<ownerDesignName>Production Planning Data Model</ownerDesignName>
<pk>true</pk>
<indexState>Primary Constraint</indexState>
<indexColumnUsage>
<colUsage columnID="5EB03632-D432-3B5C-237E-29CF216DC28F"/>
</indexColumnUsage>
</ind_PK_UK>
<ind_PK_UK class="oracle.dbtools.crest.model.design.relational.Index" id="8EFDDFF3-6377-B298-2348-860A45FD873B" name="PP_F_ACTUALS_D_DATE_D_HOUR_UOW_ID_UN">
<createdBy>34601</createdBy>
<createdTime>2013-06-26 17:49:54 UTC</createdTime>
<ownerDesignName>Production Planning Data Model</ownerDesignName>
<indexState>Unique Constraint</indexState>
<indexColumnUsage>
<colUsage columnID="52E758E8-7808-D7EA-53F5-136A903C90A7"/>
<colUsage columnID="CD7DDE3D-68EF-6DE9-EE92-B32A719122E8"/>
<colUsage columnID="BB3C52DF-89E3-23EC-1E65-57F5A8E0CC87"/>
</indexColumnUsage>
</ind_PK_UK>
<ind_PK_UK class="oracle.dbtools.crest.model.design.relational.Index" id="EC01C1ED-1CA0-D7AC-D377-FCBBFBF78293" name="PP_F_ACTUALS_ACTUALS_ID_IDX">
<createdBy>34601</createdBy>
<createdTime>2013-06-26 17:49:54 UTC</createdTime>
<ownerDesignName>Production Planning Data Model</ownerDesignName>
<indexState>Unique Plain Index</indexState>
<indexColumnUsage>
<colUsage columnID="5EB03632-D432-3B5C-237E-29CF216DC28F"/>
</indexColumnUsage>
</ind_PK_UK>
<ind_PK_UK class="oracle.dbtools.crest.model.design.relational.Index" id="78469B44-80F2-1FCF-3951-3767CC06B0CB" name="PP_F_FORECASTv1_PP_D_PRODUCTION_PLAN_HORIZON_FK">
<createdBy>34601</createdBy>
<createdTime>2013-06-26 17:49:54 UTC</createdTime>
<ownerDesignName>Production Planning Data Model</ownerDesignName>
</ind_PK_UK>
<ind_PK_UK class="oracle.dbtools.crest.model.design.relational.Index" id="B39F2A42-7514-4160-0E49-6EFF5A6FAB6C" name="PP_F_ACTUALS_PP_D_PROGRAM_FK">
<createdBy>34601</createdBy>
<createdTime>2013-06-28 17:09:39 UTC</createdTime>
<ownerDesignName>Production Planning Data Model</ownerDesignName>
</ind_PK_UK>
<ind_PK_UK class="oracle.dbtools.crest.model.design.relational.Index" id="9F0B5FB3-CDB4-0283-22FB-FC5CA4A352C4" name="PP_F_ACTUALS_PP_D_UNIT_OF_WORK_FK">
<createdBy>34601</createdBy>
<createdTime>2013-06-26 17:49:54 UTC</createdTime>
<ownerDesignName>Production Planning Data Model</ownerDesignName>
<indexState>Foreign Key</indexState>
<indexColumnUsage>
<colUsage columnID="BB3C52DF-89E3-23EC-1E65-57F5A8E0CC87"/>
</indexColumnUsage>
</ind_PK_UK>
<ind_PK_UK class="oracle.dbtools.crest.model.design.relational.Index" id="3B0F2FCD-9D60-BE2E-828C-C77D2371276A" name="PP_F_ACTUALS_PP_D_PRODUCTION_PLAN_HORIZON_FK">
<createdBy>34601</createdBy>
<createdTime>2013-06-26 17:49:54 UTC</createdTime>
<ownerDesignName>Production Planning Data Model</ownerDesignName>
<indexState>Foreign Key</indexState>
<indexColumnUsage>
<colUsage columnID="CD7DDE3D-68EF-6DE9-EE92-B32A719122E8"/>
</indexColumnUsage>
</ind_PK_UK>
<ind_PK_UK class="oracle.dbtools.crest.model.design.relational.Index" id="B57D9AB3-E466-6F63-AF0F-8ADCE3FC6A81" name="PP_F_ACTUALS_PP_D_DATES_FK">
<createdBy>34601</createdBy>
<createdTime>2013-06-26 17:49:54 UTC</createdTime>
<ownerDesignName>Production Planning Data Model</ownerDesignName>
<indexState>Foreign Key</indexState>
<indexColumnUsage>
<colUsage columnID="52E758E8-7808-D7EA-53F5-136A903C90A7"/>
</indexColumnUsage>
</ind_PK_UK>
<ind_PK_UK class="oracle.dbtools.crest.model.design.relational.Index" id="AC456B91-5B27-C504-C390-85B5A330B478" name="PP_F_ACTUALS_PP_D_GEOGRAPHY_MASTER_FK">
<createdBy>34601</createdBy>
<createdTime>2013-06-28 17:09:28 UTC</createdTime>
<ownerDesignName>Production Planning Data Model</ownerDesignName>
<indexState>Foreign Key</indexState>
<indexColumnUsage>
<colUsage columnID="1E2D38C0-B066-E120-6DBF-3697FD496337"/>
</indexColumnUsage>
</ind_PK_UK>
<ind_PK_UK class="oracle.dbtools.crest.model.design.relational.Index" id="645ECC69-A878-5B66-A6DF-648F4CD9F80B" name="PP_F_ACTUALS_PP_D_PROGRAM_FKv2">
<createdBy>34601</createdBy>
<createdTime>2013-06-28 17:10:59 UTC</createdTime>
<ownerDesignName>Production Planning Data Model</ownerDesignName>
<indexState>Foreign Key</indexState>
<indexColumnUsage>
<colUsage columnID="1DB10DB5-7EA0-EE78-4FF8-D4719A2B2BA5"/>
</indexColumnUsage>
</ind_PK_UK>
<ind_PK_UK class="oracle.dbtools.crest.model.design.relational.Index" id="89CCAC2D-3862-887D-9568-85F7D023F2E1" name="PP_F_ACTUALS_PP_D_PROJECT_FK">
<createdBy>34601</createdBy>
<createdTime>2013-06-28 17:13:31 UTC</createdTime>
<ownerDesignName>Production Planning Data Model</ownerDesignName>
<indexState>Foreign Key</indexState>
<indexColumnUsage>
<colUsage columnID="6597025F-9706-3566-51B2-5726189979FA"/>
</indexColumnUsage>
</ind_PK_UK>
</indexes>
</Table>