<?xml version = '1.0' encoding = 'UTF-8'?>
<SequenceOraclev10g class="oracle.dbtools.crest.model.design.storage.oracle.v10g.SequenceOraclev10g" name="SEQ_PPSA_ID" id="6E36F108-3AE6-C74A-077A-FE6B8B4D35C7" directorySegmentName="seg_0">
<sourceDDLFile>Prod Plan Data Model Script v5.sql</sourceDDLFile>
<createdBy>34601</createdBy>
<createdTime>2013-07-17 20:27:42 UTC</createdTime>
<ownerDesignName>Production Planning Data Model</ownerDesignName>
<cache>20</cache>
<incrementBy>1</incrementBy>
<maxValue>999999999999999999999999999</maxValue>
<minValue>1</minValue>
</SequenceOraclev10g>