<?xml version = '1.0' encoding = 'UTF-8'?>
<TableProxyOraclev11g class="oracle.dbtools.crest.model.design.storage.oracle.v11g.TableProxyOraclev11g" name="CC_S_WFM_INTERVAL" id="16302661-0F3F-D9EC-E620-73EE6B14A09C" directorySegmentName="seg_0">
<createdBy>Austin.Baker</createdBy>
<createdTime>2013-06-26 14:55:04 UTC</createdTime>
<ownerDesignName>Project Contact Center Production Planning</ownerDesignName>
<nameChanged>true</nameChanged>
<logging>YES</logging>
<columnProxies>
<ColumnProxy class="oracle.dbtools.crest.model.design.storage.oracle.v11g.ColumnProxyOraclev11g" name="HEADCOUNT_UNAVAILABLE" id="0455E83F-6861-3366-AA3D-94F30B96377D">
<createdBy>Austin.Baker</createdBy>
<createdTime>2013-06-26 14:55:04 UTC</createdTime>
<ownerDesignName>Project Contact Center Production Planning</ownerDesignName>
<defaultValue>0</defaultValue>
</ColumnProxy>
<ColumnProxy class="oracle.dbtools.crest.model.design.storage.oracle.v11g.ColumnProxyOraclev11g" name="WFM_INTERVAL_ID" id="0B099D47-0C8F-E5F4-597A-6E06704455EF">
<createdBy>Austin.Baker</createdBy>
<createdTime>2013-06-26 14:55:04 UTC</createdTime>
<ownerDesignName>Project Contact Center Production Planning</ownerDesignName>
</ColumnProxy>
<ColumnProxy class="oracle.dbtools.crest.model.design.storage.oracle.v11g.ColumnProxyOraclev11g" name="CONTACT_QUEUE_ID" id="159DB827-8721-E535-4788-37BBD83E3281">
<createdBy>Austin.Baker</createdBy>
<createdTime>2013-06-26 14:55:04 UTC</createdTime>
<ownerDesignName>Project Contact Center Production Planning</ownerDesignName>
</ColumnProxy>
<ColumnProxy class="oracle.dbtools.crest.model.design.storage.oracle.v11g.ColumnProxyOraclev11g" name="HEADCOUNT_AVAILABLE" id="1D4FC8D3-05C9-4334-3EAE-A40715D086DD">
<createdBy>Austin.Baker</createdBy>
<createdTime>2013-06-26 14:55:04 UTC</createdTime>
<ownerDesignName>Project Contact Center Production Planning</ownerDesignName>
<defaultValue>0</defaultValue>
</ColumnProxy>
<ColumnProxy class="oracle.dbtools.crest.model.design.storage.oracle.v11g.ColumnProxyOraclev11g" name="HEADCOUNT_TOTAL" id="220FF240-FE9D-8B6D-FAA8-705A731C5625">
<createdBy>Austin.Baker</createdBy>
<createdTime>2013-06-26 14:55:04 UTC</createdTime>
<ownerDesignName>Project Contact Center Production Planning</ownerDesignName>
<defaultValue>0</defaultValue>
</ColumnProxy>
<ColumnProxy class="oracle.dbtools.crest.model.design.storage.oracle.v11g.ColumnProxyOraclev11g" name="LABOR_MINUTES_WAITING" id="41A2417F-851F-0381-FC8E-B9056E875A36">
<createdBy>Austin.Baker</createdBy>
<createdTime>2013-06-26 14:55:04 UTC</createdTime>
<ownerDesignName>Project Contact Center Production Planning</ownerDesignName>
<defaultValue>0</defaultValue>
</ColumnProxy>
<ColumnProxy class="oracle.dbtools.crest.model.design.storage.oracle.v11g.ColumnProxyOraclev11g" name="EXTRACT_DT" id="5488B9F1-3C58-9F16-2CE9-B627BCDCBBE5">
<createdBy>Austin.Baker</createdBy>
<createdTime>2013-06-26 14:55:04 UTC</createdTime>
<ownerDesignName>Project Contact Center Production Planning</ownerDesignName>
</ColumnProxy>
<ColumnProxy class="oracle.dbtools.crest.model.design.storage.oracle.v11g.ColumnProxyOraclev11g" name="LAST_UPDATE_DT" id="5A43407B-D31B-B2B1-625A-B8781206EB7A">
<createdBy>Austin.Baker</createdBy>
<createdTime>2013-06-26 14:55:04 UTC</createdTime>
<ownerDesignName>Project Contact Center Production Planning</ownerDesignName>
</ColumnProxy>
<ColumnProxy class="oracle.dbtools.crest.model.design.storage.oracle.v11g.ColumnProxyOraclev11g" name="LABOR_MINUTES_TOTAL" id="7780396B-8D56-F4F7-F14B-532AC4332B0E">
<createdBy>Austin.Baker</createdBy>
<createdTime>2013-06-26 14:55:04 UTC</createdTime>
<ownerDesignName>Project Contact Center Production Planning</ownerDesignName>
<defaultValue>0</defaultValue>
</ColumnProxy>
<ColumnProxy class="oracle.dbtools.crest.model.design.storage.oracle.v11g.ColumnProxyOraclev11g" name="INTERVAL_ID" id="7D22F3E2-5B6E-86A6-C167-9A1C89E4DB90">
<createdBy>Austin.Baker</createdBy>
<createdTime>2013-06-26 14:55:04 UTC</createdTime>
<ownerDesignName>Project Contact Center Production Planning</ownerDesignName>
</ColumnProxy>
<ColumnProxy class="oracle.dbtools.crest.model.design.storage.oracle.v11g.ColumnProxyOraclev11g" name="INTERVAL_DATE" id="A5CBBF2F-4E45-2684-09BA-AB27AB6A0E8F">
<createdBy>Austin.Baker</createdBy>
<createdTime>2013-06-26 14:55:04 UTC</createdTime>
<ownerDesignName>Project Contact Center Production Planning</ownerDesignName>
</ColumnProxy>
<ColumnProxy class="oracle.dbtools.crest.model.design.storage.oracle.v11g.ColumnProxyOraclev11g" name="LABOR_MINUTES_AVAILABLE" id="DFB8EA22-681F-207A-589C-BDDC9026B587">
<createdBy>Austin.Baker</createdBy>
<createdTime>2013-06-26 14:55:04 UTC</createdTime>
<ownerDesignName>Project Contact Center Production Planning</ownerDesignName>
<defaultValue>0</defaultValue>
</ColumnProxy>
<ColumnProxy class="oracle.dbtools.crest.model.design.storage.oracle.v11g.ColumnProxyOraclev11g" name="LAST_UPDATE_BY" id="E5928477-461E-A4A7-16C8-F3D53820A0D4">
<createdBy>Austin.Baker</createdBy>
<createdTime>2013-06-26 14:55:04 UTC</createdTime>
<ownerDesignName>Project Contact Center Production Planning</ownerDesignName>
</ColumnProxy>
</columnProxies>
<indexProxies>
<IndexProxy class="oracle.dbtools.crest.model.design.storage.oracle.v10g.IndexProxyOraclev10g" name="CC_S_WFM_INTERVAL__IDXv3" id="20879A2E-20F7-994C-AE73-8F9E405A10F2">
<createdBy>Austin.Baker</createdBy>
<createdTime>2013-06-26 14:55:04 UTC</createdTime>
<ownerDesignName>Project Contact Center Production Planning</ownerDesignName>
</IndexProxy>
<IndexProxy class="oracle.dbtools.crest.model.design.storage.oracle.v10g.IndexProxyOraclev10g" name="CC_S_WFM_INTERVAL__IDXv2" id="C18B80D0-6E06-C184-E80F-62575B79A195">
<createdBy>Austin.Baker</createdBy>
<createdTime>2013-06-26 14:55:04 UTC</createdTime>
<ownerDesignName>Project Contact Center Production Planning</ownerDesignName>
</IndexProxy>
</indexProxies>
<foreignKeys>
<ForeignKey class="oracle.dbtools.crest.model.design.storage.oracle.v10g.FKProxyOraclev10g" name="CC_S_WFM_INTRVL_CC_S_INTRVL_FK" id="1C5A3162-F7DF-56B3-AF82-DE85BDDF9B87">
<createdBy>Austin.Baker</createdBy>
<createdTime>2013-06-26 14:55:04 UTC</createdTime>
<ownerDesignName>Project Contact Center Production Planning</ownerDesignName>
</ForeignKey>
<ForeignKey class="oracle.dbtools.crest.model.design.storage.oracle.v10g.FKProxyOraclev10g" name="CC_S_WFM_INTRVL_CC_S_CNTCT_Q_FK" id="F03E7E5E-15CA-69B2-D9FF-6DE298C9D914">
<createdBy>Austin.Baker</createdBy>
<createdTime>2013-06-26 14:55:04 UTC</createdTime>
<ownerDesignName>Project Contact Center Production Planning</ownerDesignName>
</ForeignKey>
</foreignKeys>
<primaryKeys>
<PrimaryKey class="oracle.dbtools.crest.model.design.storage.oracle.v10g.PKProxyOraclev10g" name="CC_S_WFM_INTERVAL_PK" id="7BC9CB91-1362-102B-97B2-C9746BADBB80">
<createdBy>Austin.Baker</createdBy>
<createdTime>2013-06-26 14:55:04 UTC</createdTime>
<ownerDesignName>Project Contact Center Production Planning</ownerDesignName>
<indexSort>SORTED</indexSort>
</PrimaryKey>
</primaryKeys>
<uniqueKeys>
<UniqueKey class="oracle.dbtools.crest.model.design.storage.oracle.v10g.UniqueOraclev10g" name="CC_S_WFM_INTERVAL__UN" id="145760CE-D6C9-C0B0-1B40-C0C3982030DB">
<createdBy>Austin.Baker</createdBy>
<createdTime>2013-06-26 14:55:04 UTC</createdTime>
<ownerDesignName>Project Contact Center Production Planning</ownerDesignName>
<indexSort>SORTED</indexSort>
</UniqueKey>
</uniqueKeys>
</TableProxyOraclev11g>