<?xml version = '1.0' encoding = 'UTF-8'?>
<TableSpaceOraclev10g class="oracle.dbtools.crest.model.design.storage.oracle.v10g.TableSpaceOraclev10g" name="MAXDAT_INDX" id="89152971-9034-B67F-74EF-C83D47E262EA" directorySegmentName="seg_0">
<createdBy>MAXUser</createdBy>
<createdTime>2014-06-04 17:29:15 UTC</createdTime>
<ownerDesignName>Project Contact Center</ownerDesignName>
<emUniformSize>0</emUniformSize>
<extentManagement>LOCAL</extentManagement>
<blockSize>8192</blockSize>
<segmentManagement>AUTO</segmentManagement>
<fileType>BIGFILE</fileType>
<dataFiles>
<DataFile class="oracle.dbtools.crest.model.design.storage.oracle.v10g.DataFileOraclev10g" name="MAXDAT_INDX_dataFile" id="73C713A9-C215-4412-08B2-C218125BE635">
<createdBy>MAXUser</createdBy>
<createdTime>2014-06-04 17:31:13 UTC</createdTime>
<comment>data file reserved for MAXDAT_INDX tablespace</comment>
<ownerDesignName>Project Contact Center</ownerDesignName>
<autoextend>ON</autoextend>
<fileName>MAXDAT_INDX.dbf</fileName>
<measureUnit>M</measureUnit>
<nextBlockSize>1024</nextBlockSize>
<reuse>NO</reuse>
<size>7</size>
</DataFile>
</dataFiles>
</TableSpaceOraclev10g>