<?xml version = '1.0' encoding = 'UTF-8'?>
<Table class="oracle.dbtools.crest.model.design.relational.Table" id="DD415D10-A549-D183-A30B-39214BC339A0" directorySegmentName="seg_0" name="D_GEOGRAPHY_MASTER">
<createdBy>cr56205</createdBy>
<createdTime>2013-07-29 19:56:50 UTC</createdTime>
<ownerDesignName>MOTS Contact Center</ownerDesignName>
<importedID>99022A06-EFF9-C80A-CC6A-BA31E2D29C96</importedID>
<pkName>CC_D_GEOGRAPHY_MASTER_PK</pkName>
<fonts>
<FontObject class="oracle.dbtools.crest.model.design.FontObjectWr">
<foType>Title</foType>
<fontStyle>1</fontStyle>
<colorRGB>-16776961</colorRGB>
</FontObject>
<FontObject class="oracle.dbtools.crest.model.design.FontObjectWr">
<foType>Column</foType>
<colorRGB>-16777216</colorRGB>
</FontObject>
<FontObject class="oracle.dbtools.crest.model.design.FontObjectWr">
<foType>Datatype</foType>
<colorRGB>-16744448</colorRGB>
</FontObject>
<FontObject class="oracle.dbtools.crest.model.design.FontObjectWr">
<foType>PK Element</foType>
<colorRGB>-16776961</colorRGB>
</FontObject>
<FontObject class="oracle.dbtools.crest.model.design.FontObjectWr">
<foType>FK Element</foType>
<colorRGB>-16777216</colorRGB>
</FontObject>
<FontObject class="oracle.dbtools.crest.model.design.FontObjectWr">
<foType>UK Element</foType>
<colorRGB>-16776961</colorRGB>
</FontObject>
<FontObject class="oracle.dbtools.crest.model.design.FontObjectWr">
<foType>Not Null</foType>
<colorRGB>-65536</colorRGB>
</FontObject>
<FontObject class="oracle.dbtools.crest.model.design.FontObjectWr">
<foType>Key</foType>
<colorRGB>-16777216</colorRGB>
</FontObject>
</fonts>
<columns>
<Column class="oracle.dbtools.crest.model.design.relational.Column" name="D_GEOGRAPHY_MASTER_ID" id="3454E2DE-E6FD-89CC-3E04-34F2B1633774" directorySegmentName="seg_1">
<sourceDDLFile>pp_ddl.sql</sourceDDLFile>
<createdBy>CB58433</createdBy>
<createdTime>2013-08-21 15:08:00 UTC</createdTime>
<comment>Surrogate key for geography records</comment>
<ownerDesignName>MOTS Contact Center</ownerDesignName>
<useDomainConstraints>false</useDomainConstraints>
<use>1</use>
<logicalDatatype>LOGDT019</logicalDatatype>
<dataTypePrecision>19</dataTypePrecision>
<dataTypeScale>0</dataTypeScale>
<autoIncrementCycle>false</autoIncrementCycle>
</Column>
<Column class="oracle.dbtools.crest.model.design.relational.Column" name="GEOGRAPHY_NAME" id="3A9F7A20-E021-825B-F8D4-B82C73EC3BB4" directorySegmentName="seg_1">
<sourceDDLFile>pp_ddl.sql</sourceDDLFile>
<createdBy>CB58433</createdBy>
<createdTime>2013-08-21 15:08:00 UTC</createdTime>
<comment>The name of the geography in unabbreviated form</comment>
<ownerDesignName>MOTS Contact Center</ownerDesignName>
<useDomainConstraints>false</useDomainConstraints>
<use>1</use>
<logicalDatatype>LOGDT024</logicalDatatype>
<dataTypeSize>250</dataTypeSize>
<autoIncrementCycle>false</autoIncrementCycle>
</Column>
<Column class="oracle.dbtools.crest.model.design.relational.Column" name="COUNTRY_ID" id="6D70C020-632E-B1A4-C1A7-E868FF96E912" directorySegmentName="seg_1">
<sourceDDLFile>pp_ddl.sql</sourceDDLFile>
<createdBy>CB58433</createdBy>
<createdTime>2013-08-21 15:08:00 UTC</createdTime>
<comment>FK to the CC_D_COUNTRY table.  This indicates to which country the geography location is associated</comment>
<ownerDesignName>MOTS Contact Center</ownerDesignName>
<useDomainConstraints>false</useDomainConstraints>
<use>1</use>
<logicalDatatype>LOGDT019</logicalDatatype>
<delegate>B8BF2EE0-2CC1-4F88-9E14-AF4ED2876EFF</delegate>
<autoIncrementCycle>false</autoIncrementCycle>
<associations>
<colAssociation fkAssociation="F259D991-22A9-393A-2480-164F39C09FEA" referredColumn="B8BF2EE0-2CC1-4F88-9E14-AF4ED2876EFF"/>
</associations>
</Column>
<Column class="oracle.dbtools.crest.model.design.relational.Column" name="STATE_ID" id="9196EE14-11BF-3427-95BC-D03442B53398" directorySegmentName="seg_1">
<sourceDDLFile>pp_ddl.sql</sourceDDLFile>
<createdBy>CB58433</createdBy>
<createdTime>2013-08-21 15:08:00 UTC</createdTime>
<comment>FK to the CC_D_STATE table.  This indicates to which state the geography location is associated</comment>
<ownerDesignName>MOTS Contact Center</ownerDesignName>
<useDomainConstraints>false</useDomainConstraints>
<use>1</use>
<logicalDatatype>LOGDT019</logicalDatatype>
<delegate>7353E4B3-1C8B-291C-7D07-45995FC83A42</delegate>
<autoIncrementCycle>false</autoIncrementCycle>
<associations>
<colAssociation fkAssociation="BABACEE4-F9B5-C560-2A37-19DFD42AE778" referredColumn="7353E4B3-1C8B-291C-7D07-45995FC83A42"/>
</associations>
</Column>
<Column class="oracle.dbtools.crest.model.design.relational.Column" name="PROVINCE_ID" id="B8F5D73D-DB32-A679-9C4E-F1E15947592F" directorySegmentName="seg_1">
<sourceDDLFile>pp_ddl.sql</sourceDDLFile>
<createdBy>CB58433</createdBy>
<createdTime>2013-08-21 15:08:00 UTC</createdTime>
<comment>FK to the CC_D_PROVINCE table.  This indicates to which province the geography location is associated</comment>
<ownerDesignName>MOTS Contact Center</ownerDesignName>
<useDomainConstraints>false</useDomainConstraints>
<use>1</use>
<logicalDatatype>LOGDT019</logicalDatatype>
<delegate>5BEB9283-A555-45DB-24C4-490C4FEA7617</delegate>
<autoIncrementCycle>false</autoIncrementCycle>
<associations>
<colAssociation fkAssociation="B1B21A37-A1BB-7027-31CA-FE24E0D4F9F1" referredColumn="5BEB9283-A555-45DB-24C4-490C4FEA7617"/>
</associations>
</Column>
<Column class="oracle.dbtools.crest.model.design.relational.Column" name="DISTRICT_ID" id="A4C92085-5EB5-1C15-2632-D06999A403FF" directorySegmentName="seg_1">
<sourceDDLFile>pp_ddl.sql</sourceDDLFile>
<createdBy>CB58433</createdBy>
<createdTime>2013-08-21 15:08:00 UTC</createdTime>
<comment>FK to the CC_D_DISTRICT table.  This indicates to which disrict the geography location is associated</comment>
<ownerDesignName>MOTS Contact Center</ownerDesignName>
<useDomainConstraints>false</useDomainConstraints>
<use>1</use>
<logicalDatatype>LOGDT019</logicalDatatype>
<delegate>9841C84B-ACBA-6EDC-A931-0656FB69CAC1</delegate>
<autoIncrementCycle>false</autoIncrementCycle>
<associations>
<colAssociation fkAssociation="B9A712EF-5D1B-C044-BB7F-B790EF8448C6" referredColumn="9841C84B-ACBA-6EDC-A931-0656FB69CAC1"/>
</associations>
</Column>
<Column class="oracle.dbtools.crest.model.design.relational.Column" name="REGION_ID" id="6F2B81B3-5DDB-2E0D-D9C7-865F2F23F5AC" directorySegmentName="seg_1">
<sourceDDLFile>pp_ddl.sql</sourceDDLFile>
<createdBy>CB58433</createdBy>
<createdTime>2013-08-21 15:08:00 UTC</createdTime>
<comment>FK to the CC_D_REGION table.  This indicates to which region the geography location is associated</comment>
<ownerDesignName>MOTS Contact Center</ownerDesignName>
<useDomainConstraints>false</useDomainConstraints>
<use>1</use>
<logicalDatatype>LOGDT019</logicalDatatype>
<delegate>5748BCA5-9800-A97B-82E1-791759A2A009</delegate>
<autoIncrementCycle>false</autoIncrementCycle>
<associations>
<colAssociation fkAssociation="A2682A32-7D4A-A656-8FF5-7B4F3003E53B" referredColumn="5748BCA5-9800-A97B-82E1-791759A2A009"/>
</associations>
</Column>
<Column class="oracle.dbtools.crest.model.design.relational.Column" name="CREATE_DATE" id="FA4E7476-7DA9-B77D-6C0C-7E644F07DCF8">
<createdBy>Austin.Baker</createdBy>
<createdTime>2013-12-31 15:32:35 UTC</createdTime>
<comment>Date this record was inserted into the dimensional table.  This is used for audit purposes.</comment>
<ownerDesignName>MOTS Contact Center</ownerDesignName>
<nullsAllowed>true</nullsAllowed>
<useDomainConstraints>false</useDomainConstraints>
<use>1</use>
<logicalDatatype>LOGDT007</logicalDatatype>
<autoIncrementCycle>false</autoIncrementCycle>
</Column>
<Column class="oracle.dbtools.crest.model.design.relational.Column" name="LAST_MODIFIED_DATE" id="BF80CD79-346D-429D-E57D-079F4FD741BF">
<createdBy>Austin.Baker</createdBy>
<createdTime>2013-12-31 15:32:35 UTC</createdTime>
<comment>The date the record was last modified.  This is used for audit purposes</comment>
<ownerDesignName>MOTS Contact Center</ownerDesignName>
<nullsAllowed>true</nullsAllowed>
<useDomainConstraints>false</useDomainConstraints>
<use>1</use>
<logicalDatatype>LOGDT007</logicalDatatype>
<autoIncrementCycle>false</autoIncrementCycle>
</Column>
</columns>
<indexes>
<ind_PK_UK class="oracle.dbtools.crest.model.design.relational.Index" id="B38AA90B-D250-A9FB-A869-C28EC7413EC9" name="D_GEOGRAPHY_MASTER_PK">
<createdBy>CB58433</createdBy>
<createdTime>2013-08-21 15:08:00 UTC</createdTime>
<ownerDesignName>MOTS Contact Center</ownerDesignName>
<pk>true</pk>
<indexState>Primary Constraint</indexState>
<indexColumnUsage>
<colUsage columnID="3454E2DE-E6FD-89CC-3E04-34F2B1633774"/>
</indexColumnUsage>
</ind_PK_UK>
<ind_PK_UK class="oracle.dbtools.crest.model.design.relational.Index" id="686069A3-0E7A-70CE-0249-BA04454A633B" name="D_GEOGRAPHY_LKUP_NAME_UN">
<createdBy>CB58433</createdBy>
<createdTime>2013-08-21 15:08:00 UTC</createdTime>
<ownerDesignName>MOTS Contact Center</ownerDesignName>
<indexState>Unique Constraint</indexState>
<indexColumnUsage>
<colUsage columnID="3A9F7A20-E021-825B-F8D4-B82C73EC3BB4"/>
</indexColumnUsage>
</ind_PK_UK>
<ind_PK_UK class="oracle.dbtools.crest.model.design.relational.Index" id="97C305E3-E903-1B89-6BD8-4EDEAD6BD3B1" name="D_GEOGRAPHY_MASTER__UN">
<createdBy>CB58433</createdBy>
<createdTime>2013-08-21 15:08:00 UTC</createdTime>
<ownerDesignName>MOTS Contact Center</ownerDesignName>
<indexState>Unique Constraint</indexState>
<indexColumnUsage>
<colUsage columnID="6D70C020-632E-B1A4-C1A7-E868FF96E912"/>
<colUsage columnID="9196EE14-11BF-3427-95BC-D03442B53398"/>
<colUsage columnID="B8F5D73D-DB32-A679-9C4E-F1E15947592F"/>
<colUsage columnID="A4C92085-5EB5-1C15-2632-D06999A403FF"/>
<colUsage columnID="6F2B81B3-5DDB-2E0D-D9C7-865F2F23F5AC"/>
</indexColumnUsage>
</ind_PK_UK>
<ind_PK_UK class="oracle.dbtools.crest.model.design.relational.Index" id="1F111BA7-C85F-D8C9-E975-D70B14554140" name="D_GM_CC_D_COUNTRY_FK">
<createdBy>CB58433</createdBy>
<createdTime>2013-08-21 15:15:34 UTC</createdTime>
<ownerDesignName>MOTS Contact Center</ownerDesignName>
<indexState>Foreign Key</indexState>
<indexColumnUsage>
<colUsage columnID="6D70C020-632E-B1A4-C1A7-E868FF96E912"/>
</indexColumnUsage>
</ind_PK_UK>
<ind_PK_UK class="oracle.dbtools.crest.model.design.relational.Index" id="FE96FADC-B9D4-F271-3AF0-C4CD743A66B3" name="D_GM_CC_D_REGION_FK">
<createdBy>CB58433</createdBy>
<createdTime>2013-08-21 15:16:29 UTC</createdTime>
<ownerDesignName>MOTS Contact Center</ownerDesignName>
<indexState>Foreign Key</indexState>
<indexColumnUsage>
<colUsage columnID="6F2B81B3-5DDB-2E0D-D9C7-865F2F23F5AC"/>
</indexColumnUsage>
</ind_PK_UK>
<ind_PK_UK class="oracle.dbtools.crest.model.design.relational.Index" id="D58264B5-F77F-975B-0449-4A3E1008D1F4" name="D_GM_CC_D_PROVINCE_FK">
<createdBy>CB58433</createdBy>
<createdTime>2013-08-21 15:16:29 UTC</createdTime>
<ownerDesignName>MOTS Contact Center</ownerDesignName>
<indexState>Foreign Key</indexState>
<indexColumnUsage>
<colUsage columnID="B8F5D73D-DB32-A679-9C4E-F1E15947592F"/>
</indexColumnUsage>
</ind_PK_UK>
<ind_PK_UK class="oracle.dbtools.crest.model.design.relational.Index" id="83F94B15-6166-D922-0CF1-460546140B52" name="D_GM_CC_D_STATE_FK">
<createdBy>CB58433</createdBy>
<createdTime>2013-08-21 15:17:20 UTC</createdTime>
<ownerDesignName>MOTS Contact Center</ownerDesignName>
<indexState>Foreign Key</indexState>
<indexColumnUsage>
<colUsage columnID="9196EE14-11BF-3427-95BC-D03442B53398"/>
</indexColumnUsage>
</ind_PK_UK>
<ind_PK_UK class="oracle.dbtools.crest.model.design.relational.Index" id="D429BF9C-78BA-FEC7-DDD2-FD79C3DCB801" name="D_GM_CC_D_DISTRICT_FK">
<createdBy>CB58433</createdBy>
<createdTime>2013-08-21 15:17:20 UTC</createdTime>
<ownerDesignName>MOTS Contact Center</ownerDesignName>
<indexState>Foreign Key</indexState>
<indexColumnUsage>
<colUsage columnID="A4C92085-5EB5-1C15-2632-D06999A403FF"/>
</indexColumnUsage>
</ind_PK_UK>
</indexes>
</Table>