<?xml version = '1.0' encoding = 'UTF-8'?>
<FKIndexAssociation class="oracle.dbtools.crest.model.design.relational.FKIndexAssociation" directorySegmentName="seg_0" id="7BD33C6B-9A51-A96E-3F59-8C88EE2C0123" name="CC_F_AGENT_DATE_D_AGENT_SUP_FK">
<createdBy>cr56205</createdBy>
<createdTime>2013-07-29 19:58:41 UTC</createdTime>
<notes>fk to supervisor agent record.</notes>
<ownerDesignName>MOTS Contact Center</ownerDesignName>
<importedID>B4DD13C6-7330-2CDA-0ACC-9B9B353F5C5F</importedID>
<containerWithKeyObject>7BF24C8E-C824-602C-0995-32E8DD4F3FA0</containerWithKeyObject>
<deleteRule>NO ACTION</deleteRule>
<localFKIndex>A2A0CCCF-D269-2780-C04E-8EEB94D2F1E5</localFKIndex>
<keyObject>0D8A269F-7FB5-2529-4689-BC3F185DB238</keyObject>
<mandatory>true</mandatory>
<transferable>true</transferable>
<columnDependencyConstraintGenerateInDDL>true</columnDependencyConstraintGenerateInDDL>
</FKIndexAssociation>