<?xml version = '1.0' encoding = 'UTF-8'?>
<SegmentOraclev10g class="oracle.dbtools.crest.model.design.storage.oracle.v10g.SegmentOraclev10g" name="MAXDAT_INDX_storage" id="568A9197-BFC9-1971-BD40-2287ED56E710" directorySegmentName="seg_0">
<createdBy>MAXUser</createdBy>
<createdTime>2014-06-03 17:48:37 UTC</createdTime>
<ownerDesignName>Project Contact Center</ownerDesignName>
<initrans>2</initrans>
<scInitialExtent>65536</scInitialExtent>
<scNextExtent>1048576</scNextExtent>
<tableSpace>F6829631-A97F-319B-1924-F3566EC4FDED</tableSpace>
</SegmentOraclev10g>