<?xml version = '1.0' encoding = 'UTF-8'?>
<Table class="oracle.dbtools.crest.model.design.relational.Table" id="060806A8-327C-FD49-D520-F432E3040365" directorySegmentName="seg_0" name="PP_D_REGION">
<createdBy>clay.rowland</createdBy>
<createdTime>2013-06-21 13:26:18 UTC</createdTime>
<commentInRDBMS>List of Regions in MAXIMUS</commentInRDBMS>
<ownerDesignName>Project Contact Center Production Planning</ownerDesignName>
<importedID>B49E0676-F2C4-1BDE-2E80-AEB65FA0C263</importedID>
<pkName>PP_D_REGION_PK</pkName>
<fonts>
<FontObject class="oracle.dbtools.crest.model.design.FontObjectWr">
<foType>Title</foType>
<fontStyle>1</fontStyle>
<colorRGB>-16776961</colorRGB>
</FontObject>
<FontObject class="oracle.dbtools.crest.model.design.FontObjectWr">
<foType>Column</foType>
<colorRGB>-16777216</colorRGB>
</FontObject>
<FontObject class="oracle.dbtools.crest.model.design.FontObjectWr">
<foType>Datatype</foType>
<colorRGB>-16744448</colorRGB>
</FontObject>
<FontObject class="oracle.dbtools.crest.model.design.FontObjectWr">
<foType>PK Element</foType>
<colorRGB>-16776961</colorRGB>
</FontObject>
<FontObject class="oracle.dbtools.crest.model.design.FontObjectWr">
<foType>FK Element</foType>
<colorRGB>-16777216</colorRGB>
</FontObject>
<FontObject class="oracle.dbtools.crest.model.design.FontObjectWr">
<foType>UK Element</foType>
<colorRGB>-16776961</colorRGB>
</FontObject>
<FontObject class="oracle.dbtools.crest.model.design.FontObjectWr">
<foType>Not Null</foType>
<colorRGB>-65536</colorRGB>
</FontObject>
<FontObject class="oracle.dbtools.crest.model.design.FontObjectWr">
<foType>Key</foType>
<colorRGB>-16777216</colorRGB>
</FontObject>
</fonts>
<columns>
<Column class="oracle.dbtools.crest.model.design.relational.Column" name="REGION_ID" id="FF866D24-2A92-1EE4-EE3E-788287E9D029">
<sourceDDLFile>pp_ddl.sql</sourceDDLFile>
<createdBy>clay.rowland</createdBy>
<createdTime>2013-06-21 13:26:18 UTC</createdTime>
<ownerDesignName>Project Contact Center Production Planning</ownerDesignName>
<importedID>39831AB6-6AEB-D39B-E7D7-DB02F9202ED0</importedID>
<use>0</use>
<logicalDatatype>LOGDT019</logicalDatatype>
<domain>4CB9DA79-71C9-835C-A6F4-A937C5D211BC</domain>
<autoIncrementCycle>false</autoIncrementCycle>
</Column>
<Column class="oracle.dbtools.crest.model.design.relational.Column" name="REGION_NAME" id="D8E03A5A-0AC8-8F3D-B967-4D90EBBA87E8">
<sourceDDLFile>pp_ddl.sql</sourceDDLFile>
<createdBy>clay.rowland</createdBy>
<createdTime>2013-06-21 13:26:18 UTC</createdTime>
<ownerDesignName>Project Contact Center Production Planning</ownerDesignName>
<importedID>825CEB53-BC4A-F9EF-2504-79714263D5B9</importedID>
<nullsAllowed>true</nullsAllowed>
<use>0</use>
<logicalDatatype>LOGDT024</logicalDatatype>
<domain>619C78C1-FFC8-87CF-678E-659D18864001</domain>
<autoIncrementCycle>false</autoIncrementCycle>
</Column>
</columns>
<indexes>
<ind_PK_UK class="oracle.dbtools.crest.model.design.relational.Index" id="A36EE9C9-8C7A-F67E-AA42-FDFAC750713D" name="PP_D_REGION_PK">
<createdBy>clay.rowland</createdBy>
<createdTime>2013-06-21 13:26:18 UTC</createdTime>
<ownerDesignName>Project Contact Center Production Planning</ownerDesignName>
<importedID>F4282DE8-5DFF-9020-F1EB-683179E11E23</importedID>
<pk>true</pk>
<indexState>Primary Constraint</indexState>
<indexColumnUsage>
<colUsage columnID="FF866D24-2A92-1EE4-EE3E-788287E9D029"/>
</indexColumnUsage>
</ind_PK_UK>
<ind_PK_UK class="oracle.dbtools.crest.model.design.relational.Index" id="F1AF08F8-FB9C-AD66-6ED8-DEBF5E1B954D" name="PP_D_REGION_UNK">
<createdBy>clay.rowland</createdBy>
<createdTime>2013-06-21 13:26:18 UTC</createdTime>
<ownerDesignName>Project Contact Center Production Planning</ownerDesignName>
<importedID>BFC87D14-B2FF-4833-42C0-E4B5FF57CF57</importedID>
<indexState>Unique Constraint</indexState>
<indexColumnUsage>
<colUsage columnID="D8E03A5A-0AC8-8F3D-B967-4D90EBBA87E8"/>
</indexColumnUsage>
</ind_PK_UK>
</indexes>
</Table>