<?xml version = '1.0' encoding = 'UTF-8'?>
<FKIndexAssociation class="oracle.dbtools.crest.model.design.relational.FKIndexAssociation" id="1D04C775-B626-552F-6EB2-15478C38361D" directorySegmentName="seg_0" name="F_FORECAST_INT_D_PPH_FK">
<createdBy>cr56205</createdBy>
<createdTime>2013-07-29 19:56:50 UTC</createdTime>
<ownerDesignName>Project Contact Center</ownerDesignName>
<importedID>9BC8E0BA-2FE0-C8FC-0F88-B1464A8C8D48</importedID>
<containerWithKeyObject>64456E51-E277-B2AA-76CF-47DE52795515</containerWithKeyObject>
<deleteRule>NO ACTION</deleteRule>
<localFKIndex>7DAE77F0-81B5-FDC9-DDBF-857CEFA035A0</localFKIndex>
<keyObject>57AA4C1F-F256-86EF-7E50-D2048A377CD6</keyObject>
<mandatory>true</mandatory>
<transferable>true</transferable>
</FKIndexAssociation>